MANIFEST.in
ez_setup.py
setup.py
open511/__init__.py
open511.egg-info/PKG-INFO
open511.egg-info/SOURCES.txt
open511.egg-info/dependency_links.txt
open511.egg-info/entry_points.txt
open511.egg-info/requires.txt
open511.egg-info/top_level.txt
open511/converter/__init__.py
open511/converter/atom.py
open511/converter/cmdline.py
open511/converter/kml.py
open511/converter/o5json.py
open511/converter/o5xml.py
open511/converter/tmdd.py
open511/tests/__init__.py
open511/tests/schedule.py
open511/tests/tmdd.py
open511/utils/__init__.py
open511/utils/input.py
open511/utils/schedule.py
open511/utils/serialization.py
open511/utils/timezone.py
open511/validator/__init__.py
open511/validator/cmdline.py
open511/validator/schema/open511.rnc
open511/validator/schema/open511.rng
open511/validator/schema/open511.schematron
open511/webtools/__init__.py
open511/webtools/templates/validator.html