Metadata-Version: 1.1
Name: open511
Version: 0.5
Summary: Tools supporting the Open511 format, which aims to make road information open and shareable.
Home-page: https://github.com/open511/open511
Author: Michael Mulley
Author-email: open511@opennorth.ca
License: MIT
Platform: UNKNOWN
Classifier: Development Status :: 4 - Beta
Classifier: Intended Audience :: Developers
Classifier: Programming Language :: Python :: 2.7
Classifier: Programming Language :: Python :: 3.5
Classifier: License :: OSI Approved :: MIT License
